<?xml version="1.0" encoding="UTF-8"?>

<!--XBRL Document Created with Wdesk from Workiva-->
<!--Copyright 2023 Workiva-->
<!--r:c7e0d2e8-48c1-4d14-a48b-b3edfb78b214,g:9d517212-9323-4e43-a3f5-6474ba90f522-->
<link:linkbase xmlns:link="http://www.xbrl.org/2003/linkbase" xmlns:xlink="http://www.w3.org/1999/xlink" xmlns:xsi="http://www.w3.org/2001/XMLSchema-instance" xsi:schemaLocation="http://www.xbrl.org/2003/linkbase http://www.xbrl.org/2003/xbrl-linkbase-2003-12-31.xsd">
  <link:roleRef roleURI="http://www.xbrl.org/2009/role/negatedPeriodStartLabel" xlink:type="simple" xlink:href="http://www.xbrl.org/lrr/role/negated-2009-12-16.xsd#negatedPeriodStartLabel"/>
  <link:roleRef roleURI="http://www.xbrl.org/2009/role/netLabel" xlink:type="simple" xlink:href="http://www.xbrl.org/lrr/role/net-2009-12-16.xsd#netLabel"/>
  <link:roleRef roleURI="http://www.xbrl.org/2009/role/negatedNetLabel" xlink:type="simple" xlink:href="http://www.xbrl.org/lrr/role/negated-2009-12-16.xsd#negatedNetLabel"/>
  <link:roleRef roleURI="http://www.xbrl.org/2009/role/negatedTerseLabel" xlink:type="simple" xlink:href="http://www.xbrl.org/lrr/role/negated-2009-12-16.xsd#negatedTerseLabel"/>
  <link:roleRef roleURI="http://www.xbrl.org/2009/role/negatedPeriodEndLabel" xlink:type="simple" xlink:href="http://www.xbrl.org/lrr/role/negated-2009-12-16.xsd#negatedPeriodEndLabel"/>
  <link:roleRef roleURI="http://www.xbrl.org/2009/role/negatedLabel" xlink:type="simple" xlink:href="http://www.xbrl.org/lrr/role/negated-2009-12-16.xsd#negatedLabel"/>
  <link:roleRef roleURI="http://www.xbrl.org/2009/role/negatedTotalLabel" xlink:type="simple" xlink:href="http://www.xbrl.org/lrr/role/negated-2009-12-16.xsd#negatedTotalLabel"/>
  <link:labelLink xlink:role="http://www.xbrl.org/2003/role/link" xlink:type="extended">
    <link:label id="lab_dei_EntityCentralIndexKey_d0b2f59e-e271-4ba8-a8e7-d3bcbd1c6b63_terseLabel_en-US" xlink:label="lab_dei_EntityCentralIndexKey" xlink:role="http://www.xbrl.org/2003/role/terseLabel" xlink:type="resource" xmlns:xml="http://www.w3.org/XML/1998/namespace" xml:lang="en-US">Entity Central Index Key</link:label>
    <link:label id="lab_dei_EntityCentralIndexKey_label_en-US" xlink:label="lab_dei_EntityCentralIndexKey" xlink:role="http://www.xbrl.org/2003/role/label" xlink:type="resource" xmlns:xml="http://www.w3.org/XML/1998/namespace" xml:lang="en-US">Entity Central Index Key</link:label>
    <link:loc xlink:type="locator" xlink:label="loc_dei_EntityCentralIndexKey" xlink:href="https://xbrl.sec.gov/dei/2022/dei-2022.xsd#dei_EntityCentralIndexKey"/>
    <link:labelArc xlink:arcrole="http://www.xbrl.org/2003/arcrole/concept-label" xlink:from="loc_dei_EntityCentralIndexKey" xlink:to="lab_dei_EntityCentralIndexKey" xlink:type="arc" order="1"/>
    <link:label id="lab_dei_EntityTaxIdentificationNumber_3e0a13a0-f9be-43c7-9834-6b586383e314_terseLabel_en-US" xlink:label="lab_dei_EntityTaxIdentificationNumber" xlink:role="http://www.xbrl.org/2003/role/terseLabel" xlink:type="resource" xmlns:xml="http://www.w3.org/XML/1998/namespace" xml:lang="en-US">Entity Tax Identification Number</link:label>
    <link:label id="lab_dei_EntityTaxIdentificationNumber_label_en-US" xlink:label="lab_dei_EntityTaxIdentificationNumber" xlink:role="http://www.xbrl.org/2003/role/label" xlink:type="resource" xmlns:xml="http://www.w3.org/XML/1998/namespace" xml:lang="en-US">Entity Tax Identification Number</link:label>
    <link:loc xlink:type="locator" xlink:label="loc_dei_EntityTaxIdentificationNumber" xlink:href="https://xbrl.sec.gov/dei/2022/dei-2022.xsd#dei_EntityTaxIdentificationNumber"/>
    <link:labelArc xlink:arcrole="http://www.xbrl.org/2003/arcrole/concept-label" xlink:from="loc_dei_EntityTaxIdentificationNumber" xlink:to="lab_dei_EntityTaxIdentificationNumber" xlink:type="arc" order="1"/>
    <link:label id="lab_dei_EntityAddressAddressLine1_a7d9dd61-828c-4922-95b1-2ddfa7346492_terseLabel_en-US" xlink:label="lab_dei_EntityAddressAddressLine1" xlink:role="http://www.xbrl.org/2003/role/terseLabel" xlink:type="resource" xmlns:xml="http://www.w3.org/XML/1998/namespace" xml:lang="en-US">Entity Address, Address Line One</link:label>
    <link:label id="lab_dei_EntityAddressAddressLine1_label_en-US" xlink:label="lab_dei_EntityAddressAddressLine1" xlink:role="http://www.xbrl.org/2003/role/label" xlink:type="resource" xmlns:xml="http://www.w3.org/XML/1998/namespace" xml:lang="en-US">Entity Address, Address Line One</link:label>
    <link:loc xlink:type="locator" xlink:label="loc_dei_EntityAddressAddressLine1" xlink:href="https://xbrl.sec.gov/dei/2022/dei-2022.xsd#dei_EntityAddressAddressLine1"/>
    <link:labelArc xlink:arcrole="http://www.xbrl.org/2003/arcrole/concept-label" xlink:from="loc_dei_EntityAddressAddressLine1" xlink:to="lab_dei_EntityAddressAddressLine1" xlink:type="arc" order="1"/>
    <link:label id="lab_dei_TradingSymbol_2a2d7170-aa75-409b-a207-cacca6940da0_terseLabel_en-US" xlink:label="lab_dei_TradingSymbol" xlink:role="http://www.xbrl.org/2003/role/terseLabel" xlink:type="resource" xmlns:xml="http://www.w3.org/XML/1998/namespace" xml:lang="en-US">Trading Symbol</link:label>
    <link:label id="lab_dei_TradingSymbol_label_en-US" xlink:label="lab_dei_TradingSymbol" xlink:role="http://www.xbrl.org/2003/role/label" xlink:type="resource" xmlns:xml="http://www.w3.org/XML/1998/namespace" xml:lang="en-US">Trading Symbol</link:label>
    <link:loc xlink:type="locator" xlink:label="loc_dei_TradingSymbol" xlink:href="https://xbrl.sec.gov/dei/2022/dei-2022.xsd#dei_TradingSymbol"/>
    <link:labelArc xlink:arcrole="http://www.xbrl.org/2003/arcrole/concept-label" xlink:from="loc_dei_TradingSymbol" xlink:to="lab_dei_TradingSymbol" xlink:type="arc" order="1"/>
    <link:label id="lab_dei_EntityFileNumber_4fd6f196-f2a5-47d8-bb19-5068f27fcd7d_terseLabel_en-US" xlink:label="lab_dei_EntityFileNumber" xlink:role="http://www.xbrl.org/2003/role/terseLabel" xlink:type="resource" xmlns:xml="http://www.w3.org/XML/1998/namespace" xml:lang="en-US">Entity File Number</link:label>
    <link:label id="lab_dei_EntityFileNumber_label_en-US" xlink:label="lab_dei_EntityFileNumber" xlink:role="http://www.xbrl.org/2003/role/label" xlink:type="resource" xmlns:xml="http://www.w3.org/XML/1998/namespace" xml:lang="en-US">Entity File Number</link:label>
    <link:loc xlink:type="locator" xlink:label="loc_dei_EntityFileNumber" xlink:href="https://xbrl.sec.gov/dei/2022/dei-2022.xsd#dei_EntityFileNumber"/>
    <link:labelArc xlink:arcrole="http://www.xbrl.org/2003/arcrole/concept-label" xlink:from="loc_dei_EntityFileNumber" xlink:to="lab_dei_EntityFileNumber" xlink:type="arc" order="1"/>
    <link:label id="lab_dei_PreCommencementIssuerTenderOffer_7cc6ef43-eb97-4dea-8563-e647424e1dd0_terseLabel_en-US" xlink:label="lab_dei_PreCommencementIssuerTenderOffer" xlink:role="http://www.xbrl.org/2003/role/terseLabel" xlink:type="resource" xmlns:xml="http://www.w3.org/XML/1998/namespace" xml:lang="en-US">Pre-commencement Issuer Tender Offer</link:label>
    <link:label id="lab_dei_PreCommencementIssuerTenderOffer_label_en-US" xlink:label="lab_dei_PreCommencementIssuerTenderOffer" xlink:role="http://www.xbrl.org/2003/role/label" xlink:type="resource" xmlns:xml="http://www.w3.org/XML/1998/namespace" xml:lang="en-US">Pre-commencement Issuer Tender Offer</link:label>
    <link:loc xlink:type="locator" xlink:label="loc_dei_PreCommencementIssuerTenderOffer" xlink:href="https://xbrl.sec.gov/dei/2022/dei-2022.xsd#dei_PreCommencementIssuerTenderOffer"/>
    <link:labelArc xlink:arcrole="http://www.xbrl.org/2003/arcrole/concept-label" xlink:from="loc_dei_PreCommencementIssuerTenderOffer" xlink:to="lab_dei_PreCommencementIssuerTenderOffer" xlink:type="arc" order="1"/>
    <link:label id="lab_dei_SolicitingMaterial_b85ba163-a911-4e66-a8d6-309d4cf4e046_terseLabel_en-US" xlink:label="lab_dei_SolicitingMaterial" xlink:role="http://www.xbrl.org/2003/role/terseLabel" xlink:type="resource" xmlns:xml="http://www.w3.org/XML/1998/namespace" xml:lang="en-US">Soliciting Material</link:label>
    <link:label id="lab_dei_SolicitingMaterial_label_en-US" xlink:label="lab_dei_SolicitingMaterial" xlink:role="http://www.xbrl.org/2003/role/label" xlink:type="resource" xmlns:xml="http://www.w3.org/XML/1998/namespace" xml:lang="en-US">Soliciting Material</link:label>
    <link:loc xlink:type="locator" xlink:label="loc_dei_SolicitingMaterial" xlink:href="https://xbrl.sec.gov/dei/2022/dei-2022.xsd#dei_SolicitingMaterial"/>
    <link:labelArc xlink:arcrole="http://www.xbrl.org/2003/arcrole/concept-label" xlink:from="loc_dei_SolicitingMaterial" xlink:to="lab_dei_SolicitingMaterial" xlink:type="arc" order="1"/>
    <link:label id="lab_dei_EntityAddressCityOrTown_f6a7af0e-e190-4d76-8bff-507a297a03ef_terseLabel_en-US" xlink:label="lab_dei_EntityAddressCityOrTown" xlink:role="http://www.xbrl.org/2003/role/terseLabel" xlink:type="resource" xmlns:xml="http://www.w3.org/XML/1998/namespace" xml:lang="en-US">Entity Address, City or Town</link:label>
    <link:label id="lab_dei_EntityAddressCityOrTown_label_en-US" xlink:label="lab_dei_EntityAddressCityOrTown" xlink:role="http://www.xbrl.org/2003/role/label" xlink:type="resource" xmlns:xml="http://www.w3.org/XML/1998/namespace" xml:lang="en-US">Entity Address, City or Town</link:label>
    <link:loc xlink:type="locator" xlink:label="loc_dei_EntityAddressCityOrTown" xlink:href="https://xbrl.sec.gov/dei/2022/dei-2022.xsd#dei_EntityAddressCityOrTown"/>
    <link:labelArc xlink:arcrole="http://www.xbrl.org/2003/arcrole/concept-label" xlink:from="loc_dei_EntityAddressCityOrTown" xlink:to="lab_dei_EntityAddressCityOrTown" xlink:type="arc" order="1"/>
    <link:label id="lab_dei_EntityIncorporationStateCountryCode_8035f7cd-f53e-45ed-8ed2-be2856545989_terseLabel_en-US" xlink:label="lab_dei_EntityIncorporationStateCountryCode" xlink:role="http://www.xbrl.org/2003/role/terseLabel" xlink:type="resource" xmlns:xml="http://www.w3.org/XML/1998/namespace" xml:lang="en-US">Entity Incorporation, State or Country Code</link:label>
    <link:label id="lab_dei_EntityIncorporationStateCountryCode_label_en-US" xlink:label="lab_dei_EntityIncorporationStateCountryCode" xlink:role="http://www.xbrl.org/2003/role/label" xlink:type="resource" xmlns:xml="http://www.w3.org/XML/1998/namespace" xml:lang="en-US">Entity Incorporation, State or Country Code</link:label>
    <link:loc xlink:type="locator" xlink:label="loc_dei_EntityIncorporationStateCountryCode" xlink:href="https://xbrl.sec.gov/dei/2022/dei-2022.xsd#dei_EntityIncorporationStateCountryCode"/>
    <link:labelArc xlink:arcrole="http://www.xbrl.org/2003/arcrole/concept-label" xlink:from="loc_dei_EntityIncorporationStateCountryCode" xlink:to="lab_dei_EntityIncorporationStateCountryCode" xlink:type="arc" order="1"/>
    <link:label id="lab_dei_LocalPhoneNumber_783d4ff7-998d-4048-88b7-eead5ee98403_terseLabel_en-US" xlink:label="lab_dei_LocalPhoneNumber" xlink:role="http://www.xbrl.org/2003/role/terseLabel" xlink:type="resource" xmlns:xml="http://www.w3.org/XML/1998/namespace" xml:lang="en-US">Local Phone Number</link:label>
    <link:label id="lab_dei_LocalPhoneNumber_label_en-US" xlink:label="lab_dei_LocalPhoneNumber" xlink:role="http://www.xbrl.org/2003/role/label" xlink:type="resource" xmlns:xml="http://www.w3.org/XML/1998/namespace" xml:lang="en-US">Local Phone Number</link:label>
    <link:loc xlink:type="locator" xlink:label="loc_dei_LocalPhoneNumber" xlink:href="https://xbrl.sec.gov/dei/2022/dei-2022.xsd#dei_LocalPhoneNumber"/>
    <link:labelArc xlink:arcrole="http://www.xbrl.org/2003/arcrole/concept-label" xlink:from="loc_dei_LocalPhoneNumber" xlink:to="lab_dei_LocalPhoneNumber" xlink:type="arc" order="1"/>
    <link:label id="lab_dei_EntityAddressPostalZipCode_30787772-e0a3-4563-a4ee-d29f61612a62_terseLabel_en-US" xlink:label="lab_dei_EntityAddressPostalZipCode" xlink:role="http://www.xbrl.org/2003/role/terseLabel" xlink:type="resource" xmlns:xml="http://www.w3.org/XML/1998/namespace" xml:lang="en-US">Entity Address, Postal Zip Code</link:label>
    <link:label id="lab_dei_EntityAddressPostalZipCode_label_en-US" xlink:label="lab_dei_EntityAddressPostalZipCode" xlink:role="http://www.xbrl.org/2003/role/label" xlink:type="resource" xmlns:xml="http://www.w3.org/XML/1998/namespace" xml:lang="en-US">Entity Address, Postal Zip Code</link:label>
    <link:loc xlink:type="locator" xlink:label="loc_dei_EntityAddressPostalZipCode" xlink:href="https://xbrl.sec.gov/dei/2022/dei-2022.xsd#dei_EntityAddressPostalZipCode"/>
    <link:labelArc xlink:arcrole="http://www.xbrl.org/2003/arcrole/concept-label" xlink:from="loc_dei_EntityAddressPostalZipCode" xlink:to="lab_dei_EntityAddressPostalZipCode" xlink:type="arc" order="1"/>
    <link:label id="lab_dei_WrittenCommunications_b09d10dc-3670-4dd8-b9e4-4a86b502920f_terseLabel_en-US" xlink:label="lab_dei_WrittenCommunications" xlink:role="http://www.xbrl.org/2003/role/terseLabel" xlink:type="resource" xmlns:xml="http://www.w3.org/XML/1998/namespace" xml:lang="en-US">Written Communications</link:label>
    <link:label id="lab_dei_WrittenCommunications_label_en-US" xlink:label="lab_dei_WrittenCommunications" xlink:role="http://www.xbrl.org/2003/role/label" xlink:type="resource" xmlns:xml="http://www.w3.org/XML/1998/namespace" xml:lang="en-US">Written Communications</link:label>
    <link:loc xlink:type="locator" xlink:label="loc_dei_WrittenCommunications" xlink:href="https://xbrl.sec.gov/dei/2022/dei-2022.xsd#dei_WrittenCommunications"/>
    <link:labelArc xlink:arcrole="http://www.xbrl.org/2003/arcrole/concept-label" xlink:from="loc_dei_WrittenCommunications" xlink:to="lab_dei_WrittenCommunications" xlink:type="arc" order="1"/>
    <link:label id="lab_dei_CityAreaCode_f1f9a283-a5af-4660-b294-6bfdaa294991_terseLabel_en-US" xlink:label="lab_dei_CityAreaCode" xlink:role="http://www.xbrl.org/2003/role/terseLabel" xlink:type="resource" xmlns:xml="http://www.w3.org/XML/1998/namespace" xml:lang="en-US">City Area Code</link:label>
    <link:label id="lab_dei_CityAreaCode_label_en-US" xlink:label="lab_dei_CityAreaCode" xlink:role="http://www.xbrl.org/2003/role/label" xlink:type="resource" xmlns:xml="http://www.w3.org/XML/1998/namespace" xml:lang="en-US">City Area Code</link:label>
    <link:loc xlink:type="locator" xlink:label="loc_dei_CityAreaCode" xlink:href="https://xbrl.sec.gov/dei/2022/dei-2022.xsd#dei_CityAreaCode"/>
    <link:labelArc xlink:arcrole="http://www.xbrl.org/2003/arcrole/concept-label" xlink:from="loc_dei_CityAreaCode" xlink:to="lab_dei_CityAreaCode" xlink:type="arc" order="1"/>
    <link:label id="lab_dei_CoverAbstract_label_en-US" xlink:label="lab_dei_CoverAbstract" xlink:role="http://www.xbrl.org/2003/role/label" xlink:type="resource" xmlns:xml="http://www.w3.org/XML/1998/namespace" xml:lang="en-US">Cover [Abstract]</link:label>
    <link:loc xlink:type="locator" xlink:label="loc_dei_CoverAbstract" xlink:href="https://xbrl.sec.gov/dei/2022/dei-2022.xsd#dei_CoverAbstract"/>
    <link:labelArc xlink:arcrole="http://www.xbrl.org/2003/arcrole/concept-label" xlink:from="loc_dei_CoverAbstract" xlink:to="lab_dei_CoverAbstract" xlink:type="arc" order="1"/>
    <link:label id="lab_dei_Security12bTitle_0344bca4-08d9-4047-88e1-b28f11d8dfa1_terseLabel_en-US" xlink:label="lab_dei_Security12bTitle" xlink:role="http://www.xbrl.org/2003/role/terseLabel" xlink:type="resource" xmlns:xml="http://www.w3.org/XML/1998/namespace" xml:lang="en-US">Title of 12(b) Security</link:label>
    <link:label id="lab_dei_Security12bTitle_label_en-US" xlink:label="lab_dei_Security12bTitle" xlink:role="http://www.xbrl.org/2003/role/label" xlink:type="resource" xmlns:xml="http://www.w3.org/XML/1998/namespace" xml:lang="en-US">Title of 12(b) Security</link:label>
    <link:loc xlink:type="locator" xlink:label="loc_dei_Security12bTitle" xlink:href="https://xbrl.sec.gov/dei/2022/dei-2022.xsd#dei_Security12bTitle"/>
    <link:labelArc xlink:arcrole="http://www.xbrl.org/2003/arcrole/concept-label" xlink:from="loc_dei_Security12bTitle" xlink:to="lab_dei_Security12bTitle" xlink:type="arc" order="1"/>
    <link:label id="lab_dei_DocumentType_6fead729-a87b-4060-9953-0eae0bb81235_terseLabel_en-US" xlink:label="lab_dei_DocumentType" xlink:role="http://www.xbrl.org/2003/role/terseLabel" xlink:type="resource" xmlns:xml="http://www.w3.org/XML/1998/namespace" xml:lang="en-US">Document Type</link:label>
    <link:label id="lab_dei_DocumentType_label_en-US" xlink:label="lab_dei_DocumentType" xlink:role="http://www.xbrl.org/2003/role/label" xlink:type="resource" xmlns:xml="http://www.w3.org/XML/1998/namespace" xml:lang="en-US">Document Type</link:label>
    <link:loc xlink:type="locator" xlink:label="loc_dei_DocumentType" xlink:href="https://xbrl.sec.gov/dei/2022/dei-2022.xsd#dei_DocumentType"/>
    <link:labelArc xlink:arcrole="http://www.xbrl.org/2003/arcrole/concept-label" xlink:from="loc_dei_DocumentType" xlink:to="lab_dei_DocumentType" xlink:type="arc" order="1"/>
    <link:label id="lab_dei_AmendmentFlag_e264cafe-1ec6-4aa8-a9d8-09855bbeb3a5_terseLabel_en-US" xlink:label="lab_dei_AmendmentFlag" xlink:role="http://www.xbrl.org/2003/role/terseLabel" xlink:type="resource" xmlns:xml="http://www.w3.org/XML/1998/namespace" xml:lang="en-US">Amendment Flag</link:label>
    <link:label id="lab_dei_AmendmentFlag_label_en-US" xlink:label="lab_dei_AmendmentFlag" xlink:role="http://www.xbrl.org/2003/role/label" xlink:type="resource" xmlns:xml="http://www.w3.org/XML/1998/namespace" xml:lang="en-US">Amendment Flag</link:label>
    <link:loc xlink:type="locator" xlink:label="loc_dei_AmendmentFlag" xlink:href="https://xbrl.sec.gov/dei/2022/dei-2022.xsd#dei_AmendmentFlag"/>
    <link:labelArc xlink:arcrole="http://www.xbrl.org/2003/arcrole/concept-label" xlink:from="loc_dei_AmendmentFlag" xlink:to="lab_dei_AmendmentFlag" xlink:type="arc" order="1"/>
    <link:label id="lab_dei_CurrentFiscalYearEndDate_e3870328-1864-4f23-b7eb-5c19418edcb3_terseLabel_en-US" xlink:label="lab_dei_CurrentFiscalYearEndDate" xlink:role="http://www.xbrl.org/2003/role/terseLabel" xlink:type="resource" xmlns:xml="http://www.w3.org/XML/1998/namespace" xml:lang="en-US">Current Fiscal Year End Date</link:label>
    <link:label id="lab_dei_CurrentFiscalYearEndDate_label_en-US" xlink:label="lab_dei_CurrentFiscalYearEndDate" xlink:role="http://www.xbrl.org/2003/role/label" xlink:type="resource" xmlns:xml="http://www.w3.org/XML/1998/namespace" xml:lang="en-US">Current Fiscal Year End Date</link:label>
    <link:loc xlink:type="locator" xlink:label="loc_dei_CurrentFiscalYearEndDate" xlink:href="https://xbrl.sec.gov/dei/2022/dei-2022.xsd#dei_CurrentFiscalYearEndDate"/>
    <link:labelArc xlink:arcrole="http://www.xbrl.org/2003/arcrole/concept-label" xlink:from="loc_dei_CurrentFiscalYearEndDate" xlink:to="lab_dei_CurrentFiscalYearEndDate" xlink:type="arc" order="1"/>
    <link:label id="lab_dei_SecurityExchangeName_5abd7459-c771-4e42-9ae2-3b23465b1b49_terseLabel_en-US" xlink:label="lab_dei_SecurityExchangeName" xlink:role="http://www.xbrl.org/2003/role/terseLabel" xlink:type="resource" xmlns:xml="http://www.w3.org/XML/1998/namespace" xml:lang="en-US">Security Exchange Name</link:label>
    <link:label id="lab_dei_SecurityExchangeName_label_en-US" xlink:label="lab_dei_SecurityExchangeName" xlink:role="http://www.xbrl.org/2003/role/label" xlink:type="resource" xmlns:xml="http://www.w3.org/XML/1998/namespace" xml:lang="en-US">Security Exchange Name</link:label>
    <link:loc xlink:type="locator" xlink:label="loc_dei_SecurityExchangeName" xlink:href="https://xbrl.sec.gov/dei/2022/dei-2022.xsd#dei_SecurityExchangeName"/>
    <link:labelArc xlink:arcrole="http://www.xbrl.org/2003/arcrole/concept-label" xlink:from="loc_dei_SecurityExchangeName" xlink:to="lab_dei_SecurityExchangeName" xlink:type="arc" order="1"/>
    <link:label id="lab_dei_EntityRegistrantName_99bd8f0a-c1c6-4dd4-b784-24e33ebca56f_terseLabel_en-US" xlink:label="lab_dei_EntityRegistrantName" xlink:role="http://www.xbrl.org/2003/role/terseLabel" xlink:type="resource" xmlns:xml="http://www.w3.org/XML/1998/namespace" xml:lang="en-US">Entity Registrant Name</link:label>
    <link:label id="lab_dei_EntityRegistrantName_label_en-US" xlink:label="lab_dei_EntityRegistrantName" xlink:role="http://www.xbrl.org/2003/role/label" xlink:type="resource" xmlns:xml="http://www.w3.org/XML/1998/namespace" xml:lang="en-US">Entity Registrant Name</link:label>
    <link:loc xlink:type="locator" xlink:label="loc_dei_EntityRegistrantName" xlink:href="https://xbrl.sec.gov/dei/2022/dei-2022.xsd#dei_EntityRegistrantName"/>
    <link:labelArc xlink:arcrole="http://www.xbrl.org/2003/arcrole/concept-label" xlink:from="loc_dei_EntityRegistrantName" xlink:to="lab_dei_EntityRegistrantName" xlink:type="arc" order="1"/>
    <link:label id="lab_dei_EntityEmergingGrowthCompany_446c8e0c-2566-43fa-8ba1-e638a8a1231a_terseLabel_en-US" xlink:label="lab_dei_EntityEmergingGrowthCompany" xlink:role="http://www.xbrl.org/2003/role/terseLabel" xlink:type="resource" xmlns:xml="http://www.w3.org/XML/1998/namespace" xml:lang="en-US">Entity Emerging Growth Company</link:label>
    <link:label id="lab_dei_EntityEmergingGrowthCompany_label_en-US" xlink:label="lab_dei_EntityEmergingGrowthCompany" xlink:role="http://www.xbrl.org/2003/role/label" xlink:type="resource" xmlns:xml="http://www.w3.org/XML/1998/namespace" xml:lang="en-US">Entity Emerging Growth Company</link:label>
    <link:loc xlink:type="locator" xlink:label="loc_dei_EntityEmergingGrowthCompany" xlink:href="https://xbrl.sec.gov/dei/2022/dei-2022.xsd#dei_EntityEmergingGrowthCompany"/>
    <link:labelArc xlink:arcrole="http://www.xbrl.org/2003/arcrole/concept-label" xlink:from="loc_dei_EntityEmergingGrowthCompany" xlink:to="lab_dei_EntityEmergingGrowthCompany" xlink:type="arc" order="1"/>
    <link:label id="lab_dei_EntityAddressStateOrProvince_7df27d3f-355a-4750-ad70-00026cb0e376_terseLabel_en-US" xlink:label="lab_dei_EntityAddressStateOrProvince" xlink:role="http://www.xbrl.org/2003/role/terseLabel" xlink:type="resource" xmlns:xml="http://www.w3.org/XML/1998/namespace" xml:lang="en-US">Entity Address, State or Province</link:label>
    <link:label id="lab_dei_EntityAddressStateOrProvince_label_en-US" xlink:label="lab_dei_EntityAddressStateOrProvince" xlink:role="http://www.xbrl.org/2003/role/label" xlink:type="resource" xmlns:xml="http://www.w3.org/XML/1998/namespace" xml:lang="en-US">Entity Address, State or Province</link:label>
    <link:loc xlink:type="locator" xlink:label="loc_dei_EntityAddressStateOrProvince" xlink:href="https://xbrl.sec.gov/dei/2022/dei-2022.xsd#dei_EntityAddressStateOrProvince"/>
    <link:labelArc xlink:arcrole="http://www.xbrl.org/2003/arcrole/concept-label" xlink:from="loc_dei_EntityAddressStateOrProvince" xlink:to="lab_dei_EntityAddressStateOrProvince" xlink:type="arc" order="1"/>
    <link:label id="lab_dei_DocumentPeriodEndDate_cd473f69-0b87-45d8-b94a-3c6d4d335d14_terseLabel_en-US" xlink:label="lab_dei_DocumentPeriodEndDate" xlink:role="http://www.xbrl.org/2003/role/terseLabel" xlink:type="resource" xmlns:xml="http://www.w3.org/XML/1998/namespace" xml:lang="en-US">Document Period End Date</link:label>
    <link:label id="lab_dei_DocumentPeriodEndDate_label_en-US" xlink:label="lab_dei_DocumentPeriodEndDate" xlink:role="http://www.xbrl.org/2003/role/label" xlink:type="resource" xmlns:xml="http://www.w3.org/XML/1998/namespace" xml:lang="en-US">Document Period End Date</link:label>
    <link:loc xlink:type="locator" xlink:label="loc_dei_DocumentPeriodEndDate" xlink:href="https://xbrl.sec.gov/dei/2022/dei-2022.xsd#dei_DocumentPeriodEndDate"/>
    <link:labelArc xlink:arcrole="http://www.xbrl.org/2003/arcrole/concept-label" xlink:from="loc_dei_DocumentPeriodEndDate" xlink:to="lab_dei_DocumentPeriodEndDate" xlink:type="arc" order="1"/>
    <link:label id="lab_dei_PreCommencementTenderOffer_21afff63-97d0-496a-9d49-f7ae2e80e135_terseLabel_en-US" xlink:label="lab_dei_PreCommencementTenderOffer" xlink:role="http://www.xbrl.org/2003/role/terseLabel" xlink:type="resource" xmlns:xml="http://www.w3.org/XML/1998/namespace" xml:lang="en-US">Pre-commencement Tender Offer</link:label>
    <link:label id="lab_dei_PreCommencementTenderOffer_label_en-US" xlink:label="lab_dei_PreCommencementTenderOffer" xlink:role="http://www.xbrl.org/2003/role/label" xlink:type="resource" xmlns:xml="http://www.w3.org/XML/1998/namespace" xml:lang="en-US">Pre-commencement Tender Offer</link:label>
    <link:loc xlink:type="locator" xlink:label="loc_dei_PreCommencementTenderOffer" xlink:href="https://xbrl.sec.gov/dei/2022/dei-2022.xsd#dei_PreCommencementTenderOffer"/>
    <link:labelArc xlink:arcrole="http://www.xbrl.org/2003/arcrole/concept-label" xlink:from="loc_dei_PreCommencementTenderOffer" xlink:to="lab_dei_PreCommencementTenderOffer" xlink:type="arc" order="1"/>
  </link:labelLink>
</link:linkbase>
